marketwatchdata/MarketWatch.py
marketwatchdata/__init__.py
tests/__init__.py
tests/test_func.py
marketwatchdata-0.0.16.dist-info/LICENSE
marketwatchdata-0.0.16.dist-info/METADATA
marketwatchdata-0.0.16.dist-info/WHEEL
marketwatchdata-0.0.16.dist-info/top_level.txt
marketwatchdata-0.0.16.dist-info/RECORD
